[
  {
    "id": "wolves-wisdom",
    "name": "Wolves’ Wisdom",
    "detachment_id": "champions-of-fenris",
    "cost": 30,
    "keyword_restrictions": [
      "Space Wolves"
    ],
    "ability_id": null,
    "is_unique": true,
    "game_version": {
      "edition": "11th",
      "dataslate": "pre-launch-provisional"
    },
    "points_provisional": true,
    "upgrade_tag": false,
    "max_targets": 1
  },
  {
    "id": "foes-fate",
    "name": "Foes’ Fate",
    "detachment_id": "champions-of-fenris",
    "cost": 15,
    "keyword_restrictions": [
      "Space Wolves"
    ],
    "ability_id": null,
    "is_unique": true,
    "game_version": {
      "edition": "11th",
      "dataslate": "pre-launch-provisional"
    },
    "points_provisional": true,
    "upgrade_tag": false,
    "max_targets": 1
  },
  {
    "id": "fangrune-pendant",
    "name": "Fangrune Pendant",
    "detachment_id": "champions-of-fenris",
    "cost": 15,
    "keyword_restrictions": [
      "Space Wolves"
    ],
    "ability_id": null,
    "is_unique": true,
    "game_version": {
      "edition": "11th",
      "dataslate": "pre-launch-provisional"
    },
    "points_provisional": true,
    "upgrade_tag": false,
    "max_targets": 1
  },
  {
    "id": "longstrider",
    "name": "Longstrider",
    "detachment_id": "champions-of-fenris",
    "cost": 20,
    "keyword_restrictions": [
      "Space Wolves"
    ],
    "ability_id": null,
    "is_unique": true,
    "game_version": {
      "edition": "11th",
      "dataslate": "pre-launch-provisional"
    },
    "points_provisional": true,
    "upgrade_tag": false,
    "max_targets": 1
  },
  {
    "id": "swift-hunter",
    "name": "Swift Hunter",
    "detachment_id": "saga-of-the-hunter",
    "cost": 20,
    "keyword_restrictions": [
      "Space Wolves"
    ],
    "ability_id": null,
    "is_unique": true,
    "game_version": {
      "edition": "11th",
      "dataslate": "pre-launch-provisional"
    },
    "points_provisional": true,
    "upgrade_tag": false,
    "max_targets": 1
  },
  {
    "id": "fenrisian-grit",
    "name": "Fenrisian Grit",
    "detachment_id": "saga-of-the-hunter",
    "cost": 15,
    "keyword_restrictions": [
      "Space Wolves"
    ],
    "ability_id": null,
    "is_unique": true,
    "game_version": {
      "edition": "11th",
      "dataslate": "pre-launch-provisional"
    },
    "points_provisional": true,
    "upgrade_tag": false,
    "max_targets": 1
  },
  {
    "id": "wolf-master",
    "name": "Wolf Master",
    "detachment_id": "saga-of-the-hunter",
    "cost": 5,
    "keyword_restrictions": [
      "Space Wolves"
    ],
    "ability_id": null,
    "is_unique": true,
    "game_version": {
      "edition": "11th",
      "dataslate": "pre-launch-provisional"
    },
    "points_provisional": true,
    "upgrade_tag": false,
    "max_targets": 1
  },
  {
    "id": "feral-rage",
    "name": "Feral Rage",
    "detachment_id": "saga-of-the-hunter",
    "cost": 10,
    "keyword_restrictions": [
      "Space Wolves"
    ],
    "ability_id": null,
    "is_unique": true,
    "game_version": {
      "edition": "11th",
      "dataslate": "pre-launch-provisional"
    },
    "points_provisional": true,
    "upgrade_tag": false,
    "max_targets": 1
  },
  {
    "id": "braggarts-steel",
    "name": "Braggart’s Steel",
    "detachment_id": "saga-of-the-bold",
    "cost": 20,
    "keyword_restrictions": [
      "Space Wolves"
    ],
    "ability_id": null,
    "is_unique": true,
    "game_version": {
      "edition": "11th",
      "dataslate": "pre-launch-provisional"
    },
    "points_provisional": true,
    "upgrade_tag": false,
    "max_targets": 1
  },
  {
    "id": "skjald",
    "name": "Skjald",
    "detachment_id": "saga-of-the-bold",
    "cost": 15,
    "keyword_restrictions": [
      "Space Wolves"
    ],
    "ability_id": null,
    "is_unique": true,
    "game_version": {
      "edition": "11th",
      "dataslate": "pre-launch-provisional"
    },
    "points_provisional": true,
    "upgrade_tag": false,
    "max_targets": 1
  },
  {
    "id": "hordeslayer",
    "name": "Hordeslayer",
    "detachment_id": "saga-of-the-bold",
    "cost": 15,
    "keyword_restrictions": [
      "Space Wolves"
    ],
    "ability_id": null,
    "is_unique": true,
    "game_version": {
      "edition": "11th",
      "dataslate": "pre-launch-provisional"
    },
    "points_provisional": true,
    "upgrade_tag": false,
    "max_targets": 1
  },
  {
    "id": "thunderwolfs-fortitude",
    "name": "Thunderwolf’s Fortitude",
    "detachment_id": "saga-of-the-bold",
    "cost": 25,
    "keyword_restrictions": [
      "Space Wolves"
    ],
    "ability_id": null,
    "is_unique": true,
    "game_version": {
      "edition": "11th",
      "dataslate": "pre-launch-provisional"
    },
    "points_provisional": true,
    "upgrade_tag": false,
    "max_targets": 1
  },
  {
    "id": "wolf-touched",
    "name": "Wolf-touched",
    "detachment_id": "saga-of-the-beastslayer",
    "cost": 15,
    "keyword_restrictions": [
      "Space Wolves"
    ],
    "ability_id": null,
    "is_unique": true,
    "game_version": {
      "edition": "11th",
      "dataslate": "pre-launch-provisional"
    },
    "points_provisional": true,
    "upgrade_tag": false,
    "max_targets": 1
  },
  {
    "id": "hunters-guile",
    "name": "Hunter’s Guile",
    "detachment_id": "saga-of-the-beastslayer",
    "cost": 20,
    "keyword_restrictions": [
      "Space Wolves"
    ],
    "ability_id": null,
    "is_unique": true,
    "game_version": {
      "edition": "11th",
      "dataslate": "pre-launch-provisional"
    },
    "points_provisional": true,
    "upgrade_tag": false,
    "max_targets": 1
  },
  {
    "id": "elders-guidance",
    "name": "Elder’s Guidance",
    "detachment_id": "saga-of-the-beastslayer",
    "cost": 20,
    "keyword_restrictions": [
      "Space Wolves"
    ],
    "ability_id": null,
    "is_unique": true,
    "game_version": {
      "edition": "11th",
      "dataslate": "pre-launch-provisional"
    },
    "points_provisional": true,
    "upgrade_tag": false,
    "max_targets": 1
  },
  {
    "id": "helm-of-the-beastslayer",
    "name": "Helm of the Beastslayer",
    "detachment_id": "saga-of-the-beastslayer",
    "cost": 15,
    "keyword_restrictions": [
      "Space Wolves"
    ],
    "ability_id": null,
    "is_unique": true,
    "game_version": {
      "edition": "11th",
      "dataslate": "pre-launch-provisional"
    },
    "points_provisional": true,
    "upgrade_tag": false,
    "max_targets": 1
  },
  {
    "id": "grimnars-mark",
    "name": "Grimnar’s Mark",
    "detachment_id": "saga-of-the-great-wolf",
    "cost": 20,
    "keyword_restrictions": [
      "Space Wolves"
    ],
    "ability_id": null,
    "is_unique": true,
    "game_version": {
      "edition": "11th",
      "dataslate": "pre-launch-provisional"
    },
    "points_provisional": true,
    "upgrade_tag": false,
    "max_targets": 1
  },
  {
    "id": "howlmaw",
    "name": "Howlmaw",
    "detachment_id": "saga-of-the-great-wolf",
    "cost": 15,
    "keyword_restrictions": [
      "Space Wolves"
    ],
    "ability_id": null,
    "is_unique": true,
    "game_version": {
      "edition": "11th",
      "dataslate": "pre-launch-provisional"
    },
    "points_provisional": true,
    "upgrade_tag": false,
    "max_targets": 1
  },
  {
    "id": "chariots-of-the-storm",
    "name": "Chariots of the Storm",
    "detachment_id": "saga-of-the-great-wolf",
    "cost": 25,
    "keyword_restrictions": [
      "Space Wolves"
    ],
    "ability_id": null,
    "is_unique": true,
    "game_version": {
      "edition": "11th",
      "dataslate": "pre-launch-provisional"
    },
    "points_provisional": true,
    "upgrade_tag": false,
    "max_targets": 1
  },
  {
    "id": "skjalds-foretelling",
    "name": "Skjald’s Foretelling",
    "detachment_id": "saga-of-the-great-wolf",
    "cost": 25,
    "keyword_restrictions": [
      "Space Wolves"
    ],
    "ability_id": null,
    "is_unique": true,
    "game_version": {
      "edition": "11th",
      "dataslate": "pre-launch-provisional"
    },
    "points_provisional": true,
    "upgrade_tag": false,
    "max_targets": 1
  }
]
