{
  "$schema": "https://json-schema.org/draft/2020-12/schema",
  "$id": "https://40kdc.dev/schemas/bundled.schema.json",
  "title": "40kdc Bundled Schemas",
  "description": "Auto-generated by tools/src/bundle-schemas.ts. Single self-contained schema for Rust codegen — do not edit by hand.",
  "$defs": {
    "entity-id": {
      "type": "string",
      "pattern": "^[a-z0-9][a-z0-9-]*[a-z0-9]$",
      "minLength": 2,
      "maxLength": 128,
      "description": "Kebab-case identifier"
    },
    "edition": {
      "type": "string",
      "pattern": "^\\d{1,2}(th)?$",
      "description": "Game edition, e.g. '10th' or '11'"
    },
    "dataslate-version": {
      "type": "string",
      "pattern": "^(\\d{4}-q[1-4]|[a-z0-9][a-z0-9-]*[a-z0-9])$",
      "description": "Dataslate version: a quarterly tag (e.g. '2025-q3') or a named kebab-case slug for non-quarterly slates (e.g. 'pre-launch-provisional')"
    },
    "keyword": {
      "type": "string",
      "minLength": 1,
      "maxLength": 64
    },
    "keyword-list": {
      "type": "array",
      "items": {
        "$ref": "#/$defs/keyword"
      },
      "uniqueItems": true
    },
    "stat-value": {
      "description": "A stat that can be a fixed number or a dice expression",
      "oneOf": [
        {
          "type": "integer",
          "minimum": 0
        },
        {
          "type": "string",
          "pattern": "^\\d*[Dd]\\d+(\\+\\d+)?$"
        }
      ]
    },
    "contributor-ref": {
      "type": "string",
      "description": "GitHub handle or '40kdc-community'"
    },
    "phase": {
      "type": "string",
      "enum": [
        "command",
        "movement",
        "shooting",
        "charge",
        "fight"
      ],
      "description": "The five official game phases. Unchanged between 10th and 11th edition — 11e reorders Pile In timing within the Fight phase but adds no top-level phase."
    },
    "phase-list": {
      "type": "array",
      "items": {
        "$ref": "#/$defs/phase"
      },
      "uniqueItems": true,
      "minItems": 1
    },
    "source-type": {
      "type": "string",
      "enum": [
        "ability",
        "stratagem",
        "enhancement",
        "detachment-rule",
        "faction-rule"
      ],
      "description": "Type of game element that is the source of an enrichment entry"
    },
    "player-turn": {
      "type": "string",
      "enum": [
        "your-turn",
        "opponent-turn",
        "either"
      ],
      "description": "Which player's turn this applies during"
    },
    "battle-size": {
      "type": "string",
      "enum": [
        "incursion",
        "strike-force"
      ],
      "description": "11e battle size, which sets the army's points limit and detachment-point budget: 'incursion' = 1000 pts / 2 detachment points; 'strike-force' = 2000 pts / 3 detachment points."
    },
    "force-disposition-id": {
      "type": "string",
      "enum": [
        "take-and-hold",
        "disruption",
        "purge-the-foe",
        "priority-assets",
        "reconnaissance"
      ],
      "description": "One of the five confirmed 11e launch Force Dispositions. Shared by force-disposition entities and the mission-matchup matrix."
    },
    "vec2": {
      "type": "object",
      "description": "A 2D point in board inches. Origin at a board corner; JSON uses y-down (downstream renderers may flip to y-up).",
      "properties": {
        "x": {
          "type": "number"
        },
        "y": {
          "type": "number"
        }
      },
      "required": [
        "x",
        "y"
      ],
      "additionalProperties": false
    },
    "game-version-ref": {
      "title": "Game Version Reference",
      "type": "object",
      "properties": {
        "edition": {
          "$ref": "#/$defs/edition"
        },
        "dataslate": {
          "$ref": "#/$defs/dataslate-version"
        }
      },
      "required": [
        "edition",
        "dataslate"
      ]
    },
    "zone-shape": {
      "description": "A zone footprint, expressed as an axis-aligned rectangle or an explicit polygon. Vertices/extent are relative to the owning element's position.",
      "oneOf": [
        {
          "type": "object",
          "properties": {
            "type": {
              "const": "rectangle"
            },
            "width": {
              "type": "number",
              "exclusiveMinimum": 0
            },
            "height": {
              "type": "number",
              "exclusiveMinimum": 0
            }
          },
          "required": [
            "type",
            "width",
            "height"
          ],
          "additionalProperties": false
        },
        {
          "type": "object",
          "properties": {
            "type": {
              "const": "polygon"
            },
            "points": {
              "type": "array",
              "items": {
                "$ref": "#/$defs/vec2"
              },
              "minItems": 3
            }
          },
          "required": [
            "type",
            "points"
          ],
          "additionalProperties": false
        }
      ]
    },
    "side": {
      "type": "string",
      "enum": [
        "attacker",
        "defender"
      ],
      "description": "Which player a zone or territory belongs to."
    },
    "deployment-pattern": {
      "title": "Deployment Pattern",
      "description": "A deployment map: per-side deployment zones, objective positions, and (11e) per-side territory polygons. Pattern geometry carries forward unchanged from 10th edition; downstream tooling (e.g. bevy-deploy-helper) consumes this as the canonical encoding.",
      "type": "object",
      "properties": {
        "id": {
          "$ref": "#/$defs/entity-id"
        },
        "name": {
          "type": "string",
          "minLength": 1,
          "maxLength": 128
        },
        "source": {
          "type": "string",
          "minLength": 1,
          "maxLength": 64,
          "description": "Mission pack or source the pattern originates from (e.g. 'leviathan')."
        },
        "description": {
          "type": "string"
        },
        "zones": {
          "type": "array",
          "minItems": 1,
          "description": "Per-side deployment zones.",
          "items": {
            "type": "object",
            "properties": {
              "player": {
                "$ref": "#/$defs/side"
              },
              "name": {
                "type": "string",
                "minLength": 1,
                "maxLength": 128
              },
              "shape": {
                "$ref": "#/$defs/zone-shape"
              },
              "position": {
                "$ref": "#/$defs/vec2"
              },
              "color": {
                "type": "string",
                "pattern": "^#[0-9a-fA-F]{6}$",
                "description": "Hex render color for the zone overlay."
              }
            },
            "required": [
              "player",
              "shape",
              "position"
            ],
            "additionalProperties": false
          }
        },
        "territories": {
          "type": "array",
          "description": "11e per-side territory polygons, mirroring the deployment-zone shape (e.g. the band between a deployment zone and the midline). Empty until authored.",
          "items": {
            "type": "object",
            "properties": {
              "player": {
                "$ref": "#/$defs/side"
              },
              "shape": {
                "$ref": "#/$defs/zone-shape"
              },
              "position": {
                "$ref": "#/$defs/vec2"
              }
            },
            "required": [
              "player",
              "shape",
              "position"
            ],
            "additionalProperties": false
          }
        },
        "objectives": {
          "type": "array",
          "description": "Objective-marker positions on the board.",
          "items": {
            "$ref": "#/$defs/vec2"
          }
        },
        "recommended_terrain_layout_ids": {
          "type": "array",
          "uniqueItems": true,
          "description": "Ids of recommended terrain-layout entities (resolved once terrain-layout data is authored).",
          "items": {
            "$ref": "#/$defs/entity-id"
          }
        },
        "game_version": {
          "$ref": "#/$defs/game-version-ref"
        }
      },
      "required": [
        "id",
        "name",
        "zones",
        "game_version"
      ],
      "additionalProperties": false
    },
    "detachment": {
      "title": "Detachment",
      "description": "A detachment option within a faction, providing a detachment rule, enhancements, and stratagems.",
      "type": "object",
      "properties": {
        "id": {
          "$ref": "#/$defs/entity-id"
        },
        "name": {
          "type": "string",
          "minLength": 1,
          "maxLength": 128
        },
        "faction_id": {
          "$ref": "#/$defs/entity-id"
        },
        "detachment_rule_id": {
          "oneOf": [
            {
              "$ref": "#/$defs/entity-id"
            },
            {
              "type": "null"
            }
          ]
        },
        "detachment_points": {
          "oneOf": [
            {
              "type": "integer",
              "minimum": 1,
              "maximum": 3
            },
            {
              "type": "null"
            }
          ],
          "description": "11e: the detachment-point cost (1–3) charged against the army's detachment-point budget. null when not yet assigned."
        },
        "force_dispositions": {
          "type": "array",
          "items": {
            "$ref": "#/$defs/entity-id"
          },
          "uniqueItems": true,
          "description": "11e: ids of the Force Disposition entities this detachment grants. Empty until assigned."
        },
        "enhancement_ids": {
          "type": "array",
          "items": {
            "$ref": "#/$defs/entity-id"
          }
        },
        "stratagem_ids": {
          "type": "array",
          "items": {
            "$ref": "#/$defs/entity-id"
          }
        },
        "restrictions": {
          "oneOf": [
            {
              "type": "object",
              "properties": {
                "required_keywords": {
                  "$ref": "#/$defs/keyword-list"
                },
                "excluded_keywords": {
                  "$ref": "#/$defs/keyword-list"
                },
                "notes": {
                  "type": "string"
                }
              },
              "additionalProperties": false
            },
            {
              "type": "null"
            }
          ]
        },
        "game_version": {
          "$ref": "#/$defs/game-version-ref"
        }
      },
      "required": [
        "id",
        "name",
        "faction_id",
        "game_version"
      ],
      "additionalProperties": false
    },
    "enhancement": {
      "title": "Enhancement",
      "description": "A purchasable upgrade for a character unit, provided by a detachment.",
      "type": "object",
      "properties": {
        "id": {
          "$ref": "#/$defs/entity-id"
        },
        "name": {
          "type": "string",
          "minLength": 1,
          "maxLength": 128
        },
        "detachment_id": {
          "$ref": "#/$defs/entity-id"
        },
        "cost": {
          "type": "integer",
          "minimum": 0
        },
        "points_provisional": {
          "type": "boolean",
          "default": false,
          "description": "True when the cost is carried over provisionally (e.g. seeded from a prior edition during migration) and not yet confirmed against the current dataslate."
        },
        "upgrade_tag": {
          "type": "boolean",
          "default": false,
          "description": "11e: when true, this enhancement applies to up to `max_targets` non-character units while counting as a single Enhancement choice."
        },
        "max_targets": {
          "type": "integer",
          "minimum": 1,
          "default": 1,
          "description": "Number of units this enhancement may be applied to. Only meaningful when `upgrade_tag` is true; defaults to 1."
        },
        "keyword_restrictions": {
          "$ref": "#/$defs/keyword-list"
        },
        "exclusion_keywords": {
          "oneOf": [
            {
              "$ref": "#/$defs/keyword-list"
            },
            {
              "type": "null"
            }
          ]
        },
        "ability_id": {
          "oneOf": [
            {
              "$ref": "#/$defs/entity-id"
            },
            {
              "type": "null"
            }
          ]
        },
        "is_unique": {
          "type": "boolean",
          "default": true
        },
        "game_version": {
          "$ref": "#/$defs/game-version-ref"
        }
      },
      "required": [
        "id",
        "name",
        "detachment_id",
        "cost",
        "game_version"
      ],
      "additionalProperties": false
    },
    "faction": {
      "title": "Faction",
      "description": "A playable faction or sub-faction.",
      "type": "object",
      "properties": {
        "id": {
          "$ref": "#/$defs/entity-id"
        },
        "name": {
          "type": "string",
          "minLength": 1,
          "maxLength": 128
        },
        "parent_faction_id": {
          "oneOf": [
            {
              "$ref": "#/$defs/entity-id"
            },
            {
              "type": "null"
            }
          ]
        },
        "game_version": {
          "$ref": "#/$defs/game-version-ref"
        },
        "keywords": {
          "$ref": "#/$defs/keyword-list"
        },
        "aliases": {
          "type": "array",
          "items": {
            "type": "string"
          }
        },
        "faction_rule_id": {
          "oneOf": [
            {
              "$ref": "#/$defs/entity-id"
            },
            {
              "type": "null"
            }
          ],
          "description": "Reference to the faction-wide ability (e.g., Oath of Moment)"
        }
      },
      "required": [
        "id",
        "name",
        "game_version"
      ],
      "additionalProperties": false
    },
    "force-disposition": {
      "title": "Force Disposition",
      "description": "A 11e strategic-intent tag granted by detachments. Players compare dispositions at game start to determine the shared mission; asymmetric primary objectives result.",
      "type": "object",
      "properties": {
        "id": {
          "$ref": "#/$defs/force-disposition-id",
          "description": "One of the five confirmed launch Force Dispositions."
        },
        "name": {
          "type": "string",
          "minLength": 1,
          "maxLength": 128
        },
        "text": {
          "type": "string",
          "minLength": 1,
          "description": "Community-authored description of the disposition's effect (original prose only — no reproduced rules text)."
        },
        "game_version": {
          "$ref": "#/$defs/game-version-ref"
        }
      },
      "required": [
        "id",
        "name",
        "game_version"
      ],
      "additionalProperties": false
    },
    "game-version": {
      "title": "Game Version",
      "type": "object",
      "properties": {
        "edition": {
          "$ref": "#/$defs/edition"
        },
        "dataslate": {
          "$ref": "#/$defs/dataslate-version"
        },
        "effective_date": {
          "type": "string",
          "format": "date"
        },
        "label": {
          "type": "string"
        },
        "supersedes": {
          "oneOf": [
            {
              "$ref": "#/$defs/dataslate-version"
            },
            {
              "type": "null"
            }
          ]
        }
      },
      "required": [
        "edition",
        "dataslate",
        "effective_date"
      ],
      "additionalProperties": false
    },
    "leader-attachment": {
      "title": "Leader Attachment",
      "description": "Defines which character units can attach to which bodyguard units.",
      "type": "object",
      "properties": {
        "leader_id": {
          "$ref": "#/$defs/entity-id"
        },
        "eligible_bodyguard_ids": {
          "type": "array",
          "items": {
            "$ref": "#/$defs/entity-id"
          },
          "minItems": 1
        },
        "game_version": {
          "$ref": "#/$defs/game-version-ref"
        }
      },
      "required": [
        "leader_id",
        "eligible_bodyguard_ids",
        "game_version"
      ],
      "additionalProperties": false
    },
    "mission-matchup": {
      "title": "Mission Matchup",
      "description": "One cell of the 11e Force Disposition matrix: given the player's own Force Disposition and their opponent's, the mission that player plays. Mirrors a single row on a physical Force Disposition card. The (disposition, opponent_disposition) pair is the conceptual key; compound uniqueness across entries is a data convention, not enforced by this schema.",
      "type": "object",
      "properties": {
        "id": {
          "$ref": "#/$defs/entity-id"
        },
        "disposition": {
          "$ref": "#/$defs/force-disposition-id",
          "description": "The player's own Force Disposition."
        },
        "opponent_disposition": {
          "$ref": "#/$defs/force-disposition-id",
          "description": "The opponent's Force Disposition."
        },
        "mission_id": {
          "$ref": "#/$defs/entity-id",
          "description": "Id of the mission entity the player plays for this disposition pairing."
        },
        "game_version": {
          "$ref": "#/$defs/game-version-ref"
        }
      },
      "required": [
        "id",
        "disposition",
        "opponent_disposition",
        "mission_id",
        "game_version"
      ],
      "additionalProperties": false
    },
    "mission": {
      "title": "Mission",
      "description": "An 11e primary mission (the objective a player scores). Which mission a player plays is selected by the Force Disposition matchup matrix (see mission-matchup), keyed on the player's own disposition and their opponent's. Victory points are capped per game and per battle round.",
      "type": "object",
      "properties": {
        "id": {
          "$ref": "#/$defs/entity-id"
        },
        "name": {
          "type": "string",
          "minLength": 1,
          "maxLength": 128
        },
        "source": {
          "type": "string",
          "minLength": 1,
          "maxLength": 64,
          "description": "Mission pack or source the mission originates from."
        },
        "description": {
          "type": "string",
          "description": "Community-authored mission/objective summary (original prose only — no reproduced rules text)."
        },
        "vp_per_game_cap": {
          "type": "integer",
          "minimum": 0,
          "default": 45,
          "description": "Maximum primary VP scorable across the whole game. 11e default is 45."
        },
        "vp_per_round_cap": {
          "type": "integer",
          "minimum": 0,
          "default": 15,
          "description": "Maximum primary VP scorable in a single battle round. 11e default is 15."
        },
        "deployment_pattern_ids": {
          "type": "array",
          "uniqueItems": true,
          "description": "Ids of the deployment-pattern entities (maps) this mission can be played on. Empty until the per-mission maps are confirmed.",
          "items": {
            "$ref": "#/$defs/entity-id"
          }
        },
        "game_version": {
          "$ref": "#/$defs/game-version-ref"
        }
      },
      "required": [
        "id",
        "name",
        "game_version"
      ],
      "additionalProperties": false
    },
    "scoring-trigger": {
      "type": "object",
      "description": "When a VP award is evaluated. A bare `phase` is the legacy shorthand for 'during this phase'; richer triggers add `timing` (the moment within a phase/turn/game), `player_turn`, and a `battle_round` window. A card's section headers map onto these: 'ANY BATTLE ROUND' omits `battle_round`; 'SECOND BATTLE ROUND ONWARDS' is { min: 2 }; 'END OF THE BATTLE' is timing: end-of-battle.",
      "properties": {
        "phase": {
          "$ref": "#/$defs/phase",
          "description": "The phase the trigger is relative to. Required when `timing` is start-of-phase or end-of-phase; omitted for turn- or battle-level timings."
        },
        "timing": {
          "type": "string",
          "enum": [
            "start-of-turn",
            "end-of-turn",
            "start-of-phase",
            "end-of-phase",
            "end-of-battle"
          ],
          "description": "The moment the award is checked. 'End of your turn' = end-of-turn; 'End of your Command phase' = end-of-phase with phase: command; 'End of the battle' = end-of-battle."
        },
        "player_turn": {
          "$ref": "#/$defs/player-turn"
        },
        "battle_round": {
          "type": "object",
          "description": "Battle-round window in which the trigger is active. Absent means any battle round (1-5). 'Second battle round onwards' is { min: 2 }.",
          "properties": {
            "min": {
              "type": "integer",
              "minimum": 1,
              "maximum": 5
            },
            "max": {
              "type": "integer",
              "minimum": 1,
              "maximum": 5
            }
          },
          "minProperties": 1,
          "additionalProperties": false
        }
      },
      "minProperties": 1,
      "allOf": [
        {}
      ],
      "additionalProperties": false
    },
    "army-composition-predicate": {
      "type": "object",
      "description": "A draw-time predicate over an army list (not runtime board state, so deliberately NOT the Ability DSL condition). Used to gate when_drawn operations such as redraws. Example: a card that is void unless the opponent fields a large unit (10e 'Cull the Horde' redrew when the opponent had no unit of 14+ models) is { subject: 'opponent', quantifier: 'none', unit_filter: { model_count_min: 14 } } with operation 'redraw'.",
      "properties": {
        "subject": {
          "type": "string",
          "enum": [
            "self",
            "opponent"
          ],
          "description": "Whose army list the predicate inspects."
        },
        "quantifier": {
          "type": "string",
          "enum": [
            "any",
            "none"
          ],
          "description": "Whether the army must contain ('any') or lack ('none') a unit matching unit_filter for the predicate to hold."
        },
        "unit_filter": {
          "type": "object",
          "description": "Criteria a unit in the army must satisfy to match. All present criteria must hold (logical AND).",
          "properties": {
            "model_count_min": {
              "type": "integer",
              "minimum": 1
            },
            "model_count_max": {
              "type": "integer",
              "minimum": 1
            },
            "wounds_min": {
              "type": "integer",
              "minimum": 1
            },
            "keywords": {
              "$ref": "#/$defs/keyword-list"
            }
          },
          "minProperties": 1,
          "additionalProperties": false
        }
      },
      "required": [
        "subject",
        "quantifier",
        "unit_filter"
      ],
      "additionalProperties": false
    },
    "secondary-card": {
      "title": "Secondary Card",
      "description": "An 11e mission card. The deck-level rule (draw 2 per turn, keep unscored cards) is separate and not modelled here. This is the per-card shape: an optional on-draw deck operation, an optional player action, and zero or more VP-award blocks. Primary mission cards reuse this shape via card_type. Mechanic blocks reference the Ability DSL; prose is community-authored (no reproduced rules text).",
      "type": "object",
      "properties": {
        "id": {
          "$ref": "#/$defs/entity-id"
        },
        "name": {
          "type": "string",
          "minLength": 1,
          "maxLength": 128
        },
        "card_type": {
          "type": "string",
          "enum": [
            "secondary",
            "primary"
          ],
          "default": "secondary",
          "description": "Whether this is a secondary card or a primary mission card (which reuses this shape)."
        },
        "subtype": {
          "type": "string",
          "minLength": 1,
          "maxLength": 64,
          "description": "Finer classification within the deck (e.g. a category or tactical/fixed split). Free-form — not enum-locked until 11e categories are confirmed."
        },
        "when_drawn": {
          "type": "object",
          "description": "Optional deck operation performed when this card is drawn (e.g. redraw, swap). Distinct from combat effects — deck operations have no combat target, so they are not modelled via the Ability DSL effect language. If `condition` is present, the operation fires only when the predicate holds.",
          "properties": {
            "operation": {
              "type": "string",
              "enum": [
                "reshuffle",
                "replace",
                "redraw",
                "draw-extra",
                "swap"
              ],
              "description": "The deck manipulation this card triggers on draw."
            },
            "card_ids": {
              "type": "array",
              "uniqueItems": true,
              "description": "Other cards this operation references, by id.",
              "items": {
                "$ref": "#/$defs/entity-id"
              }
            },
            "condition": {
              "$ref": "#/$defs/army-composition-predicate",
              "description": "Draw-time army-composition predicate gating the operation (e.g. redraw when the opponent lacks a qualifying unit)."
            }
          },
          "required": [
            "operation"
          ],
          "additionalProperties": false
        },
        "action": {
          "type": "object",
          "description": "Optional player action the card enables.",
          "properties": {
            "starts": {
              "$ref": "#/$defs/phase",
              "description": "Phase in which the action can be started."
            },
            "player_turn": {
              "$ref": "#/$defs/player-turn"
            },
            "units": {
              "$ref": "#/$defs/condition",
              "description": "Eligibility predicate for which units may perform the action."
            },
            "use_limit": {
              "type": "integer",
              "minimum": 1,
              "description": "Maximum number of times the action may be performed."
            },
            "completes": {
              "$ref": "#/$defs/condition",
              "description": "Predicate for when the action is considered complete."
            },
            "effect": {
              "$ref": "#/$defs/effect",
              "description": "Effect applied when the action completes (e.g. terrain-area-tag to mark transient state on a terrain piece)."
            }
          },
          "additionalProperties": false
        },
        "awards": {
          "type": "array",
          "minItems": 1,
          "description": "VP-award blocks: each scores when `trigger` fires and the optional `when` condition holds. An award scores either a flat `vp` or a count-scaled `vp_per` (VP per instance of the thing named by `per`). Awards accrue independently and sum; a card's '+ ... CUMULATIVE' rows are modelled as separate awards flagged `cumulative` for faithful round-trip.",
          "items": {
            "type": "object",
            "properties": {
              "trigger": {
                "$ref": "#/$defs/scoring-trigger"
              },
              "when": {
                "$ref": "#/$defs/condition"
              },
              "vp": {
                "type": "integer",
                "minimum": 0,
                "description": "Flat VP scored when the award fires."
              },
              "vp_per": {
                "type": "integer",
                "minimum": 0,
                "description": "VP scored per instance of the thing named by `per` (e.g. 1 VP per operation marker within range of a controlled objective)."
              },
              "per": {
                "type": "string",
                "minLength": 1,
                "maxLength": 128,
                "description": "What `vp_per` counts, as a kebab-case descriptor (e.g. 'operation-marker-within-range-of-controlled-central-objective'). Required when `vp_per` is present."
              },
              "per_max": {
                "type": "integer",
                "minimum": 1,
                "description": "Optional cap on how many instances `vp_per` counts."
              },
              "cumulative": {
                "type": "boolean",
                "default": false,
                "description": "Marks an award the card shows as an additive '+' bonus to the preceding award in the same trigger block (the card's CUMULATIVE rows). Purely descriptive — all awards accrue independently and are summed."
              }
            },
            "oneOf": [
              {
                "required": [
                  "vp"
                ]
              },
              {
                "required": [
                  "vp_per",
                  "per"
                ]
              }
            ],
            "required": [
              "trigger"
            ],
            "additionalProperties": false
          }
        },
        "text": {
          "type": "string",
          "description": "Community-authored card description (original prose only — no reproduced rules text)."
        },
        "game_version": {
          "$ref": "#/$defs/game-version-ref"
        }
      },
      "required": [
        "id",
        "name",
        "game_version"
      ],
      "additionalProperties": false
    },
    "stratagem": {
      "title": "Stratagem",
      "description": "A CP-costed ability usable during specific game phases.",
      "type": "object",
      "properties": {
        "id": {
          "$ref": "#/$defs/entity-id"
        },
        "name": {
          "type": "string",
          "minLength": 1,
          "maxLength": 128
        },
        "category": {
          "type": "string",
          "enum": [
            "core",
            "detachment"
          ],
          "description": "Whether this is a universal core stratagem or tied to a specific detachment"
        },
        "type": {
          "type": "string",
          "enum": [
            "battle-tactic",
            "strategic-ploy",
            "epic-deed",
            "wargear"
          ],
          "description": "GW-printed stratagem category from the card"
        },
        "detachment_id": {
          "oneOf": [
            {
              "$ref": "#/$defs/entity-id"
            },
            {
              "type": "null"
            }
          ],
          "description": "Null for core stratagems"
        },
        "cp_cost": {
          "type": "integer",
          "minimum": 0,
          "maximum": 4
        },
        "phases": {
          "$ref": "#/$defs/phase-list"
        },
        "player_turn": {
          "$ref": "#/$defs/player-turn"
        },
        "timing": {
          "type": "string",
          "enum": [
            "once-per-phase",
            "once-per-turn",
            "once-per-battle",
            "unlimited"
          ]
        },
        "target_restrictions": {
          "oneOf": [
            {
              "type": "object",
              "properties": {
                "required_keywords": {
                  "$ref": "#/$defs/keyword-list"
                },
                "excluded_keywords": {
                  "$ref": "#/$defs/keyword-list"
                },
                "notes": {
                  "type": "string"
                }
              },
              "additionalProperties": false
            },
            {
              "type": "null"
            }
          ]
        },
        "ability_id": {
          "oneOf": [
            {
              "$ref": "#/$defs/entity-id"
            },
            {
              "type": "null"
            }
          ]
        },
        "game_version": {
          "$ref": "#/$defs/game-version-ref"
        }
      },
      "required": [
        "id",
        "name",
        "category",
        "type",
        "cp_cost",
        "phases",
        "player_turn",
        "timing",
        "game_version"
      ],
      "additionalProperties": false
    },
    "footprint": {
      "description": "A terrain piece's 2D footprint, relative to the piece's `position`. Axis-aligned rectangle, right triangle (right angle at the local origin, legs along +x/+y), or an explicit polygon. GW's standard templates (e.g. 7\"×11.5\" rectangles, 8\"×11.5\" right triangles, 6\"×4\" rectangles, 10\"×2.5\" and 6\"×2\" lines) are all expressible here; lines are thin rectangles.",
      "oneOf": [
        {
          "type": "object",
          "properties": {
            "type": {
              "const": "rectangle"
            },
            "width": {
              "type": "number",
              "exclusiveMinimum": 0
            },
            "height": {
              "type": "number",
              "exclusiveMinimum": 0
            }
          },
          "required": [
            "type",
            "width",
            "height"
          ],
          "additionalProperties": false
        },
        {
          "type": "object",
          "properties": {
            "type": {
              "const": "right-triangle"
            },
            "width": {
              "type": "number",
              "exclusiveMinimum": 0
            },
            "height": {
              "type": "number",
              "exclusiveMinimum": 0
            }
          },
          "required": [
            "type",
            "width",
            "height"
          ],
          "additionalProperties": false
        },
        {
          "type": "object",
          "properties": {
            "type": {
              "const": "polygon"
            },
            "points": {
              "type": "array",
              "items": {
                "$ref": "#/$defs/vec2"
              },
              "minItems": 3
            }
          },
          "required": [
            "type",
            "points"
          ],
          "additionalProperties": false
        }
      ]
    },
    "terrain-area-keyword": {
      "type": "string",
      "enum": [
        "obscuring",
        "hidden",
        "plunging-fire"
      ],
      "description": "An 11e terrain-area keyword. Confirmed launch set; extend as further keywords publish on dataslate."
    },
    "piece": {
      "type": "object",
      "description": "One terrain feature placed on the board.",
      "properties": {
        "name": {
          "type": "string",
          "minLength": 1,
          "maxLength": 128
        },
        "footprint": {
          "$ref": "#/$defs/footprint"
        },
        "position": {
          "$ref": "#/$defs/vec2",
          "description": "Board-inch placement of the footprint's local origin."
        },
        "rotation_degrees": {
          "type": "number",
          "minimum": 0,
          "exclusiveMaximum": 360,
          "description": "Clockwise rotation of the footprint about `position`. Absent or 0 means axis-aligned."
        },
        "template": {
          "type": "string",
          "minLength": 1,
          "maxLength": 64,
          "description": "Optional descriptive label for the GW standard template this piece uses (e.g. 'large-ruin', 'long-wall'). Free-form, not enum-locked — the geometry in `footprint` is authoritative."
        },
        "height_inches": {
          "type": "number",
          "minimum": 0,
          "description": "Height of the piece in inches. Gates Plunging Fire (a piece 3\" or taller confers +1 BS on ground-level targets)."
        },
        "terrain_area_keywords": {
          "type": "array",
          "uniqueItems": true,
          "description": "Terrain-area keywords this piece's area carries.",
          "items": {
            "$ref": "#/$defs/terrain-area-keyword"
          }
        },
        "link_group": {
          "type": "string",
          "minLength": 1,
          "maxLength": 64,
          "description": "Pieces sharing a `link_group` value are linked terrain — treated as a single terrain feature (and, where an objective sits among them, a single objective)."
        },
        "is_objective": {
          "type": "boolean",
          "default": false,
          "description": "Whether this piece carries an objective marker."
        },
        "objective": {
          "type": "object",
          "description": "Objective-marker metadata. Only meaningful when `is_objective` is true.",
          "properties": {
            "position": {
              "$ref": "#/$defs/vec2",
              "description": "Board-inch position of the marker. Absent means the piece's `position`."
            },
            "control_range_inches": {
              "type": "number",
              "exclusiveMinimum": 0,
              "description": "Range from the marker within which models contribute to control."
            }
          },
          "additionalProperties": false
        }
      },
      "required": [
        "footprint",
        "position"
      ],
      "additionalProperties": false
    },
    "terrain-layout": {
      "title": "Terrain Layout",
      "description": "A recommended arrangement of terrain pieces on the board, independent of the deployment map (a deployment-pattern references the layouts it recommends via recommended_terrain_layout_ids). Geometry is the source of truth; the GW standard piece templates are expressed as explicit footprints, with an optional descriptive `template` label. Footprints are deliberately open (not enum-locked) — the launch catalog and its size are unconfirmed, so this models any shape rather than a fixed set. No layout data is authored yet.",
      "type": "object",
      "properties": {
        "id": {
          "$ref": "#/$defs/entity-id"
        },
        "name": {
          "type": "string",
          "minLength": 1,
          "maxLength": 128
        },
        "source": {
          "type": "string",
          "minLength": 1,
          "maxLength": 64,
          "description": "Mission pack or source the layout originates from."
        },
        "description": {
          "type": "string"
        },
        "pieces": {
          "type": "array",
          "description": "Terrain pieces composing the layout. May be empty while a layout is registered by name ahead of its confirmed geometry.",
          "items": {
            "$ref": "#/$defs/piece"
          }
        },
        "game_version": {
          "$ref": "#/$defs/game-version-ref"
        }
      },
      "required": [
        "id",
        "name",
        "game_version"
      ],
      "additionalProperties": false
    },
    "unit-composition": {
      "title": "Unit Composition",
      "description": "Describes the internal model-type breakdown of a unit.",
      "type": "object",
      "properties": {
        "unit_id": {
          "$ref": "#/$defs/entity-id"
        },
        "models": {
          "type": "array",
          "items": {
            "type": "object",
            "properties": {
              "name": {
                "type": "string",
                "minLength": 1
              },
              "profile_name": {
                "oneOf": [
                  {
                    "type": "string",
                    "minLength": 1
                  },
                  {
                    "type": "null"
                  }
                ]
              },
              "min": {
                "type": "integer",
                "minimum": 0
              },
              "max": {
                "type": "integer",
                "minimum": 1
              },
              "default_weapon_ids": {
                "type": "array",
                "items": {
                  "$ref": "#/$defs/entity-id"
                }
              },
              "is_leader_model": {
                "type": "boolean",
                "default": false
              }
            },
            "required": [
              "name",
              "min",
              "max"
            ],
            "additionalProperties": false
          },
          "minItems": 1
        },
        "game_version": {
          "$ref": "#/$defs/game-version-ref"
        }
      },
      "required": [
        "unit_id",
        "models",
        "game_version"
      ],
      "additionalProperties": false
    },
    "unit": {
      "title": "Unit",
      "description": "A unit datasheet entry with stat profiles and point costs.",
      "type": "object",
      "properties": {
        "id": {
          "$ref": "#/$defs/entity-id"
        },
        "name": {
          "type": "string",
          "minLength": 1,
          "maxLength": 128
        },
        "faction_id": {
          "$ref": "#/$defs/entity-id"
        },
        "role": {
          "type": "string",
          "enum": [
            "character",
            "battleline",
            "dedicated-transport",
            "fortification",
            "allied",
            "epic-hero"
          ],
          "description": "Battlefield role from the datasheet header. Unit types (Infantry, Vehicle, etc.) belong in keywords."
        },
        "attachment_role": {
          "oneOf": [
            {
              "enum": [
                "leader",
                "support"
              ]
            },
            {
              "type": "null"
            }
          ],
          "description": "Character attachment role (11e). 'support' implies the unit is only legal when attached to a host unit (cannot be taken solo); 'leader' is valid as a standalone list entry. null/absent for non-attaching units."
        },
        "profiles": {
          "type": "array",
          "items": {
            "type": "object",
            "properties": {
              "name": {
                "type": "string",
                "description": "Profile name (e.g., 'Wounded' for degrading)"
              },
              "M": {
                "$ref": "#/$defs/stat-value"
              },
              "T": {
                "type": "integer",
                "minimum": 1
              },
              "W": {
                "type": "integer",
                "minimum": 1
              },
              "Sv": {
                "type": "integer",
                "minimum": 2,
                "maximum": 7
              },
              "invuln_sv": {
                "oneOf": [
                  {
                    "type": "integer",
                    "minimum": 2,
                    "maximum": 6
                  },
                  {
                    "type": "null"
                  }
                ]
              },
              "Ld": {
                "type": "integer",
                "minimum": 2,
                "maximum": 10
              },
              "OC": {
                "type": "integer",
                "minimum": 0
              }
            },
            "required": [
              "M",
              "T",
              "W",
              "Sv",
              "Ld",
              "OC"
            ]
          },
          "minItems": 1
        },
        "points": {
          "type": "array",
          "items": {
            "type": "object",
            "properties": {
              "models": {
                "type": "integer",
                "minimum": 1
              },
              "cost": {
                "type": "integer",
                "minimum": 0
              }
            },
            "required": [
              "models",
              "cost"
            ]
          }
        },
        "points_provisional": {
          "type": "boolean",
          "default": false,
          "description": "True when point costs are carried over provisionally (e.g. seeded from a prior edition during migration) and not yet confirmed against the current dataslate."
        },
        "keywords": {
          "$ref": "#/$defs/keyword-list"
        },
        "faction_keywords": {
          "$ref": "#/$defs/keyword-list"
        },
        "base_size_mm": {
          "oneOf": [
            {
              "type": "object",
              "properties": {
                "shape": {
                  "enum": [
                    "round",
                    "oval"
                  ]
                },
                "diameter": {
                  "type": "number"
                },
                "width": {
                  "type": "number"
                },
                "length": {
                  "type": "number"
                }
              },
              "required": [
                "shape"
              ]
            },
            {
              "type": "null"
            }
          ]
        },
        "model_count": {
          "type": "object",
          "properties": {
            "min": {
              "type": "integer",
              "minimum": 1
            },
            "max": {
              "type": "integer",
              "minimum": 1
            }
          },
          "required": [
            "min",
            "max"
          ]
        },
        "weapon_ids": {
          "type": "array",
          "items": {
            "$ref": "#/$defs/entity-id"
          }
        },
        "ability_ids": {
          "type": "array",
          "items": {
            "$ref": "#/$defs/entity-id"
          }
        },
        "transport_capacity": {
          "oneOf": [
            {
              "type": "object",
              "properties": {
                "capacity": {
                  "type": "integer",
                  "minimum": 1
                },
                "keyword_restrictions": {
                  "oneOf": [
                    {
                      "$ref": "#/$defs/keyword-list"
                    },
                    {
                      "type": "null"
                    }
                  ]
                },
                "exclusion_keywords": {
                  "oneOf": [
                    {
                      "$ref": "#/$defs/keyword-list"
                    },
                    {
                      "type": "null"
                    }
                  ]
                }
              },
              "required": [
                "capacity"
              ],
              "additionalProperties": false
            },
            {
              "type": "null"
            }
          ]
        },
        "game_version": {
          "$ref": "#/$defs/game-version-ref"
        },
        "is_legend": {
          "type": "boolean",
          "default": false
        }
      },
      "required": [
        "id",
        "name",
        "faction_id",
        "profiles",
        "game_version"
      ],
      "additionalProperties": false
    },
    "wargear-option": {
      "title": "Wargear Option",
      "description": "A weapon substitution option available to models within a unit.",
      "type": "object",
      "properties": {
        "id": {
          "$ref": "#/$defs/entity-id"
        },
        "unit_id": {
          "$ref": "#/$defs/entity-id"
        },
        "model_constraint": {
          "oneOf": [
            {
              "type": "object",
              "properties": {
                "model_name": {
                  "type": "string",
                  "minLength": 1
                },
                "per_n_models": {
                  "type": "integer",
                  "minimum": 1
                },
                "max_count": {
                  "type": "integer",
                  "minimum": 1
                }
              },
              "additionalProperties": false
            },
            {
              "type": "null"
            }
          ]
        },
        "replaces": {
          "type": "array",
          "items": {
            "$ref": "#/$defs/entity-id"
          },
          "minItems": 1,
          "description": "Weapon IDs being removed"
        },
        "replacement": {
          "type": "array",
          "items": {
            "$ref": "#/$defs/entity-id"
          },
          "minItems": 1,
          "description": "Weapon IDs being added"
        },
        "is_free": {
          "type": "boolean",
          "default": true
        },
        "additional_cost": {
          "oneOf": [
            {
              "type": "integer",
              "minimum": 0
            },
            {
              "type": "null"
            }
          ]
        },
        "game_version": {
          "$ref": "#/$defs/game-version-ref"
        }
      },
      "required": [
        "id",
        "unit_id",
        "replaces",
        "replacement",
        "game_version"
      ],
      "additionalProperties": false
    },
    "weapon-keyword": {
      "title": "Weapon Keyword",
      "description": "Catalog entry for a weapon keyword (Lethal Hits, Sustained Hits N, Anti-X N+, etc.). Each weapon profile references entries here via {keyword_id, parameters?} instead of carrying free-text strings. The optional `effect` describes the keyword's game mechanic in the Ability DSL; null when the behaviour is faction-specific flavour not yet modelled.",
      "type": "object",
      "properties": {
        "id": {
          "$ref": "#/$defs/entity-id"
        },
        "name": {
          "type": "string",
          "minLength": 1,
          "maxLength": 128
        },
        "required_parameters": {
          "type": "array",
          "description": "Parameter keys that must be supplied at each reference site, in the order they would appear in a printed datasheet (e.g. Anti-INFANTRY 4+ → ['target_keyword', 'threshold']).",
          "items": {
            "type": "string",
            "enum": [
              "value",
              "target_keyword",
              "threshold"
            ]
          },
          "uniqueItems": true,
          "maxItems": 3
        },
        "effect": {
          "oneOf": [
            {
              "$ref": "#/$defs/effect"
            },
            {
              "type": "null"
            }
          ],
          "description": "Mechanical effect of this keyword. Null when the behaviour is faction-specific flavour not yet expressible in the DSL — engines treat such references as no-op buffs and may surface them as 'cannot auto-apply'."
        },
        "game_version": {
          "$ref": "#/$defs/game-version-ref"
        }
      },
      "required": [
        "id",
        "name",
        "required_parameters",
        "effect",
        "game_version"
      ],
      "additionalProperties": false
    },
    "weapon": {
      "title": "Weapon",
      "description": "A weapon entry with one or more stat profiles (e.g., standard and overcharge modes).",
      "type": "object",
      "properties": {
        "id": {
          "$ref": "#/$defs/entity-id"
        },
        "name": {
          "type": "string",
          "minLength": 1,
          "maxLength": 128
        },
        "type": {
          "enum": [
            "ranged",
            "melee"
          ]
        },
        "profiles": {
          "type": "array",
          "items": {
            "type": "object",
            "properties": {
              "name": {
                "type": "string",
                "minLength": 1,
                "maxLength": 128
              },
              "range": {
                "oneOf": [
                  {
                    "type": "integer",
                    "minimum": 0
                  },
                  {
                    "type": "string",
                    "const": "Melee"
                  }
                ]
              },
              "stats": {
                "type": "object",
                "properties": {
                  "A": {
                    "$ref": "#/$defs/stat-value"
                  },
                  "BS": {
                    "oneOf": [
                      {
                        "type": "integer",
                        "minimum": 2,
                        "maximum": 6
                      },
                      {
                        "type": "null"
                      }
                    ]
                  },
                  "WS": {
                    "oneOf": [
                      {
                        "type": "integer",
                        "minimum": 2,
                        "maximum": 6
                      },
                      {
                        "type": "null"
                      }
                    ]
                  },
                  "S": {
                    "$ref": "#/$defs/stat-value"
                  },
                  "AP": {
                    "type": "integer"
                  },
                  "D": {
                    "$ref": "#/$defs/stat-value"
                  }
                },
                "required": [
                  "A",
                  "S",
                  "AP",
                  "D"
                ]
              },
              "keywords": {
                "type": "array",
                "description": "References into the weapon-keyword catalog. Each entry names the catalog id and supplies parameter values (e.g. `Sustained Hits 1` → `{keyword_id: 'sustained-hits', parameters: {value: 1}}`).",
                "items": {
                  "type": "object",
                  "properties": {
                    "keyword_id": {
                      "$ref": "#/$defs/entity-id"
                    },
                    "parameters": {
                      "type": "object",
                      "description": "Reference-site parameters conforming to the catalog entry's required_parameters. Only the three documented keys are accepted; any other key is invalid.",
                      "properties": {
                        "value": {
                          "$ref": "#/$defs/stat-value"
                        },
                        "target_keyword": {
                          "type": "string",
                          "minLength": 1,
                          "maxLength": 64
                        },
                        "threshold": {
                          "type": "integer",
                          "minimum": 2,
                          "maximum": 6
                        }
                      },
                      "additionalProperties": false
                    }
                  },
                  "required": [
                    "keyword_id"
                  ],
                  "additionalProperties": false
                }
              }
            },
            "required": [
              "name",
              "stats"
            ],
            "additionalProperties": false
          },
          "minItems": 1
        },
        "game_version": {
          "$ref": "#/$defs/game-version-ref"
        }
      },
      "required": [
        "id",
        "name",
        "type",
        "profiles",
        "game_version"
      ],
      "additionalProperties": false
    },
    "ability": {
      "title": "Ability DSL Entry",
      "description": "Community-authored structured representation of what a game ability does. NOT GW text.",
      "type": "object",
      "properties": {
        "ability_id": {
          "$ref": "#/$defs/entity-id"
        },
        "name": {
          "type": "string"
        },
        "authored_by": {
          "$ref": "#/$defs/contributor-ref"
        },
        "game_version": {
          "$ref": "#/$defs/game-version-ref"
        },
        "version": {
          "$ref": "#/$defs/dataslate-version"
        },
        "supersedes": {
          "oneOf": [
            {
              "$ref": "#/$defs/dataslate-version"
            },
            {
              "type": "null"
            }
          ]
        },
        "unit_ids": {
          "type": "array",
          "items": {
            "$ref": "#/$defs/entity-id"
          }
        },
        "faction_id": {
          "oneOf": [
            {
              "$ref": "#/$defs/entity-id"
            },
            {
              "type": "null"
            }
          ],
          "description": "For faction-type abilities, the faction this rule belongs to"
        },
        "detachment_id": {
          "oneOf": [
            {
              "$ref": "#/$defs/entity-id"
            },
            {
              "type": "null"
            }
          ],
          "description": "For detachment/enhancement/stratagem-type abilities, the associated detachment"
        },
        "ability_type": {
          "type": "string",
          "enum": [
            "core",
            "faction",
            "detachment",
            "unit",
            "enhancement",
            "stratagem"
          ]
        },
        "behavior": {
          "type": "string",
          "enum": [
            "passive",
            "activated",
            "reactive",
            "aura"
          ],
          "description": "How this ability interacts with the game flow — not a runtime predicate"
        },
        "effect": {
          "$ref": "#/$defs/effect"
        },
        "scope": {
          "$ref": "#/$defs/scope"
        },
        "interactions": {
          "type": "array",
          "items": {
            "type": "object",
            "properties": {
              "ability_ref": {
                "$ref": "#/$defs/entity-id"
              },
              "type": {
                "type": "string",
                "enum": [
                  "conflicts-with",
                  "combos-with",
                  "superseded-by",
                  "requires",
                  "replaces"
                ]
              },
              "notes": {
                "type": "string"
              }
            },
            "required": [
              "ability_ref",
              "type"
            ]
          }
        },
        "disputed": {
          "type": "boolean",
          "default": false
        },
        "dispute_notes": {
          "type": "string"
        },
        "community_notes": {
          "type": "string"
        }
      },
      "required": [
        "ability_id",
        "name",
        "authored_by",
        "game_version",
        "effect",
        "scope"
      ],
      "additionalProperties": false
    },
    "condition-node": {
      "oneOf": [
        {
          "$ref": "#/$defs/simple-condition"
        },
        {
          "$ref": "#/$defs/compound-condition"
        }
      ]
    },
    "simple-condition": {
      "type": "object",
      "$comment": "Board/meta-state and scoring predicates. `parameters` is intentionally open (additionalProperties: true); each type documents its own param convention. Scoring predicates added for mission cards: `units-destroyed` { side: 'enemy'|'friendly', window: 'this-turn'|'previous-turn', count_min: int } — at least count_min units of `side` were destroyed in `window`. `units-destroyed-comparison` { subject: {side, window}, comparator: 'greater-than'|'greater-or-equal', reference: {side, window} } — compares two destruction tallies (e.g. more enemy units destroyed this turn than friendly last turn). `objective-majority` { relative_to: 'opponent' } — you control more objectives than the named party. `controls-objective` params: { count_min: int, objective_role?: 'central', exclude?: 'home', objective?: 'opponent-home' }.",
      "properties": {
        "type": {
          "type": "string",
          "enum": [
            "phase-is",
            "timing-is",
            "player-turn-is",
            "unit-below-starting-strength",
            "unit-below-half-strength",
            "unit-has-keyword",
            "unit-within-range-of",
            "model-is-leader",
            "target-has-keyword",
            "charged-this-turn",
            "advanced-this-turn",
            "remained-stationary",
            "is-battle-shocked",
            "has-lost-wounds",
            "opponent-unit-within-range",
            "within-range-of-objective",
            "attack-is-type",
            "has-fought-this-phase",
            "destroyed-by-attack-type",
            "controls-objective",
            "is-attached",
            "terrain-area-control",
            "engagement-state",
            "territory-control",
            "fights-first",
            "disposition-matches",
            "units-destroyed",
            "units-destroyed-comparison",
            "objective-majority"
          ]
        },
        "parameters": {
          "type": "object",
          "additionalProperties": true
        },
        "negated": {
          "type": "boolean",
          "default": false
        }
      },
      "required": [
        "type"
      ]
    },
    "compound-condition": {
      "type": "object",
      "properties": {
        "operator": {
          "type": "string",
          "enum": [
            "and",
            "or",
            "not"
          ]
        },
        "operands": {
          "type": "array",
          "items": {
            "$ref": "#/$defs/condition-node"
          },
          "minItems": 1
        }
      },
      "required": [
        "operator",
        "operands"
      ]
    },
    "condition": {
      "title": "Ability Condition",
      "$ref": "#/$defs/condition-node"
    },
    "effect-node": {
      "oneOf": [
        {
          "$ref": "#/$defs/single-effect"
        },
        {
          "$ref": "#/$defs/choice-effect"
        },
        {
          "$ref": "#/$defs/sequence-effect"
        },
        {
          "$ref": "#/$defs/dice-gated-effect"
        },
        {
          "$ref": "#/$defs/conditional-effect"
        },
        {
          "$ref": "#/$defs/dice-pool-allocation-effect"
        }
      ]
    },
    "single-effect": {
      "type": "object",
      "properties": {
        "type": {
          "type": "string",
          "enum": [
            "stat-modifier",
            "roll-modifier",
            "re-roll",
            "mortal-wounds",
            "feel-no-pain",
            "invulnerable-save",
            "ward",
            "keyword-grant",
            "movement-modifier",
            "deep-strike",
            "fallback-and-act",
            "fight-first",
            "fight-last",
            "shoot-on-death",
            "fight-on-death",
            "objective-control-modifier",
            "leadership-modifier",
            "damage-reduction",
            "attack-restriction",
            "ability-grant",
            "cp-gain",
            "cp-refund",
            "model-destruction",
            "resurrection",
            "resource-gain",
            "resource-spend",
            "charge-roll-modifier",
            "terrain-area-tag",
            "bs-modifier",
            "engagement-passthrough"
          ]
        },
        "target": {
          "type": "string",
          "enum": [
            "self",
            "bearer",
            "unit",
            "attached-unit",
            "attacker",
            "defender",
            "friendly-within-aura",
            "enemy-within-aura",
            "all-friendly",
            "all-enemy"
          ]
        },
        "modifier": {
          "type": "object",
          "additionalProperties": true
        }
      },
      "required": [
        "type",
        "target"
      ],
      "$comment": "When `type` is `re-roll`, `modifier` must carry `roll` (string) and `subset` (`ones` | `all-failures`). Rerolls always target failures; the subset decides whether only 1s are rerolled or every failed die. The constraint is enforced by AJV at validation time and stripped from the codegen bundle (typify can't model if/then/else) — the generated TS/Rust types therefore see `modifier` as an open object, matching its other-`type` callers. When `type` is `feel-no-pain`, `modifier` carries `threshold` (the FNP save target) and optionally `scope` ∈ {`all`, `mortal`}; an absent scope defaults to `all` (fires on every unsaved wound). The two scopes compose independently against the mortal-wound stream.",
      "allOf": [
        {}
      ]
    },
    "choice-effect": {
      "type": "object",
      "properties": {
        "type": {
          "const": "choice"
        },
        "options": {
          "type": "array",
          "items": {
            "$ref": "#/$defs/effect-node"
          },
          "minItems": 2
        },
        "choice_label": {
          "type": "string"
        }
      },
      "required": [
        "type",
        "options"
      ]
    },
    "sequence-effect": {
      "type": "object",
      "properties": {
        "type": {
          "const": "sequence"
        },
        "steps": {
          "type": "array",
          "items": {
            "$ref": "#/$defs/effect-node"
          },
          "minItems": 1
        }
      },
      "required": [
        "type",
        "steps"
      ]
    },
    "dice-gated-effect": {
      "type": "object",
      "properties": {
        "type": {
          "const": "dice-gated"
        },
        "dice": {
          "type": "string",
          "description": "Dice expression, e.g. 'D6', '2D6'"
        },
        "threshold": {
          "oneOf": [
            {
              "type": "integer"
            },
            {
              "type": "string",
              "enum": [
                "leadership",
                "toughness",
                "save"
              ]
            }
          ],
          "description": "Fixed threshold or model characteristic to compare against"
        },
        "comparison": {
          "type": "string",
          "enum": [
            "gte",
            "lte",
            "gt",
            "lt",
            "eq"
          ],
          "default": "gte"
        },
        "on_success": {
          "oneOf": [
            {
              "$ref": "#/$defs/effect-node"
            },
            {
              "type": "null"
            }
          ]
        },
        "on_fail": {
          "oneOf": [
            {
              "$ref": "#/$defs/effect-node"
            },
            {
              "type": "null"
            }
          ]
        }
      },
      "required": [
        "type",
        "dice",
        "threshold"
      ]
    },
    "conditional-effect": {
      "type": "object",
      "properties": {
        "type": {
          "const": "conditional"
        },
        "condition": {
          "$ref": "#/$defs/condition"
        },
        "effect": {
          "$ref": "#/$defs/effect-node"
        }
      },
      "required": [
        "type",
        "condition",
        "effect"
      ]
    },
    "dice-pool-allocation-effect": {
      "type": "object",
      "properties": {
        "type": {
          "const": "dice-pool-allocation"
        },
        "pool": {
          "type": "object",
          "properties": {
            "count": {
              "type": "integer",
              "minimum": 1
            },
            "die": {
              "type": "string"
            }
          },
          "required": [
            "count",
            "die"
          ]
        },
        "max_activations": {
          "type": "integer",
          "minimum": 1
        },
        "options": {
          "type": "array",
          "items": {
            "type": "object",
            "properties": {
              "name": {
                "type": "string"
              },
              "requirement": {
                "type": "object",
                "properties": {
                  "type": {
                    "type": "string",
                    "enum": [
                      "pair",
                      "triple",
                      "single",
                      "run"
                    ]
                  },
                  "min_value": {
                    "type": "integer",
                    "minimum": 1,
                    "maximum": 6
                  }
                },
                "required": [
                  "type",
                  "min_value"
                ]
              },
              "effect": {
                "$ref": "#/$defs/effect-node"
              }
            },
            "required": [
              "name",
              "requirement",
              "effect"
            ]
          },
          "minItems": 1
        }
      },
      "required": [
        "type",
        "pool",
        "max_activations",
        "options"
      ]
    },
    "effect": {
      "title": "Ability Effect",
      "$ref": "#/$defs/effect-node"
    },
    "scope": {
      "title": "Ability Scope",
      "type": "object",
      "properties": {
        "range": {
          "type": "string",
          "enum": [
            "self",
            "unit",
            "attached",
            "aura-6",
            "aura-9",
            "aura-12",
            "aura-custom",
            "engagement-range",
            "any-visible",
            "any-on-battlefield",
            "terrain-within-range"
          ]
        },
        "duration": {
          "type": "string",
          "enum": [
            "phase",
            "turn",
            "battle-round",
            "battle",
            "until-next-command-phase",
            "one-use",
            "permanent"
          ]
        },
        "range_inches": {
          "type": "number"
        }
      },
      "required": [
        "range",
        "duration"
      ]
    },
    "interaction-flag": {
      "title": "Interaction Flag",
      "type": "object",
      "properties": {
        "ability_a": {
          "$ref": "#/$defs/entity-id"
        },
        "ability_b": {
          "$ref": "#/$defs/entity-id"
        },
        "interaction_type": {
          "type": "string",
          "enum": [
            "conflicts",
            "combos",
            "sequencing-dependent",
            "stacks",
            "does-not-stack",
            "replaces"
          ]
        },
        "resolution": {
          "type": "string"
        },
        "faq_reference": {
          "type": "string"
        },
        "disputed": {
          "type": "boolean",
          "default": false
        },
        "game_version": {
          "$ref": "#/$defs/game-version-ref"
        },
        "authored_by": {
          "$ref": "#/$defs/contributor-ref"
        }
      },
      "required": [
        "ability_a",
        "ability_b",
        "interaction_type",
        "game_version"
      ]
    },
    "phase-mapping": {
      "title": "Phase Mapping",
      "type": "object",
      "properties": {
        "source_id": {
          "$ref": "#/$defs/entity-id"
        },
        "source_type": {
          "$ref": "#/$defs/source-type"
        },
        "phases": {
          "$ref": "#/$defs/phase-list"
        },
        "game_version": {
          "$ref": "#/$defs/game-version-ref"
        },
        "authored_by": {
          "$ref": "#/$defs/contributor-ref"
        }
      },
      "required": [
        "source_id",
        "source_type",
        "phases",
        "game_version"
      ]
    },
    "resource-pool": {
      "title": "Resource Pool",
      "description": "A faction's resource system (Miracle Dice, Pain tokens, Blessings dice pool, etc.).",
      "type": "object",
      "properties": {
        "id": {
          "$ref": "#/$defs/entity-id"
        },
        "name": {
          "type": "string",
          "minLength": 1,
          "maxLength": 128
        },
        "faction_id": {
          "$ref": "#/$defs/entity-id"
        },
        "pool_type": {
          "type": "string",
          "enum": [
            "token",
            "dice-pool",
            "counter"
          ]
        },
        "generation": {
          "type": "array",
          "items": {
            "type": "object",
            "properties": {
              "condition": {
                "$ref": "#/$defs/condition"
              },
              "amount": {
                "$ref": "#/$defs/stat-value"
              }
            },
            "required": [
              "condition",
              "amount"
            ]
          }
        },
        "max_size": {
          "oneOf": [
            {
              "type": "integer",
              "minimum": 1
            },
            {
              "type": "null"
            }
          ]
        },
        "game_version": {
          "$ref": "#/$defs/game-version-ref"
        }
      },
      "required": [
        "id",
        "name",
        "faction_id",
        "pool_type",
        "game_version"
      ],
      "additionalProperties": false
    },
    "timing-flag": {
      "title": "Timing Flag",
      "type": "object",
      "properties": {
        "source_id": {
          "$ref": "#/$defs/entity-id"
        },
        "source_type": {
          "$ref": "#/$defs/source-type"
        },
        "timing": {
          "type": "string",
          "enum": [
            "start-of-phase",
            "end-of-phase",
            "before-hit-roll",
            "after-hit-roll",
            "before-wound-roll",
            "after-wound-roll",
            "before-save-roll",
            "after-save-roll",
            "before-damage-roll",
            "after-damage-roll",
            "before-charge-roll",
            "after-charge-roll",
            "before-advance-roll",
            "after-advance-roll",
            "before-battle-shock",
            "after-battle-shock",
            "on-unit-selected",
            "on-unit-destroyed",
            "on-model-destroyed",
            "on-damage-allocated"
          ]
        },
        "game_version": {
          "$ref": "#/$defs/game-version-ref"
        },
        "authored_by": {
          "$ref": "#/$defs/contributor-ref"
        }
      },
      "required": [
        "source_id",
        "source_type",
        "timing",
        "game_version"
      ]
    }
  }
}
